README.md
setup.py
pyabinit/__init__.py
pyabinit/constant.py
pyabinit.egg-info/PKG-INFO
pyabinit.egg-info/SOURCES.txt
pyabinit.egg-info/dependency_links.txt
pyabinit.egg-info/not-zip-safe
pyabinit.egg-info/requires.txt
pyabinit.egg-info/top_level.txt