Metadata-Version: 2.1
Name: pyabinit
Version: 0.0.2
Summary: pyabinit(https://www.abinit.org/)
Home-page: https://gitee.com/alkemie_gjwang/pyabinit
Author: Guanjie Wang
Author-email: gjwang@buaa.edu.cn
License: MIT
Platform: UNKNOWN
